powertb.py
powertb-1.0.0.dist-info/METADATA
powertb-1.0.0.dist-info/WHEEL
powertb-1.0.0.dist-info/top_level.txt
powertb-1.0.0.dist-info/RECORD
