Metadata-Version: 2.1
Name: powertb
Version: 1.0.0
Summary: Give your tracebacks superpowers!
Home-page: https://github.com/windelbouwman/powertb
Author: Windel Bouwman
Author-email: windel.bouwman@gmail.com
License: UNKNOWN
Platform: UNKNOWN
Classifier: Development Status :: 4 - Beta
Classifier: Programming Language :: Python
Classifier: Intended Audience :: Developers
